flet_django/.DS_Store
flet_django/__init__.py
flet_django/admin.py
flet_django/apps.py
flet_django/compat.py
flet_django/controls/__init__.py
flet_django/controls/modelform.py
flet_django/controls/modeltable.py
flet_django/management/__init__.py
flet_django/management/commands/__init__.py
flet_django/management/commands/run_app.py
flet_django/middlewares.py
flet_django/models.py
flet_django/navigation.py
flet_django/pages.py
flet_django/routes.py
flet_django/serializers.py
flet_django/types.py
flet_django/urls.py
flet_django/views.py
flet_django-0.4.5.dist-info/LICENSE
flet_django-0.4.5.dist-info/METADATA
flet_django-0.4.5.dist-info/WHEEL
flet_django-0.4.5.dist-info/RECORD
