Metadata-Version: 2.1
Name: flet-django
Version: 0.4.5
Summary: Django Flutter Framework.
Home-page: https://marysia.app
License: MIT
Author: beret
Author-email: beret@hipisi.org.pl
Maintainer: Marysia Software Limited
Maintainer-email: office@marysia.app
Requires-Python: >=3.10,<4.0
Classifier: Development Status :: 4 - Beta
Classifier: Environment :: MacOS X
Classifier: Environment :: Web Environment
Classifier: Environment :: WebAssembly
Classifier: Environment :: Win32 (MS Windows)
Classifier: Environment :: X11 Applications
Classifier: Framework :: Django
Classifier: Framework :: Django :: 4.0
Classifier: Framework :: Django :: 4.1
Classifier: License :: OSI Approved :: MIT License
Classifier: Operating System :: OS Independent
Classifier: Programming Language :: Other
Classifier: Programming Language :: Python :: 3
Classifier: Programming Language :: Python :: 3.10
Classifier: Programming Language :: Python :: 3.11
Classifier: Programming Language :: Python :: 3 :: Only
Classifier: Programming Language :: Python :: 3.10
Classifier: Programming Language :: Python :: 3.11
Classifier: Programming Language :: Python :: 3.12
Classifier: Topic :: Desktop Environment
Requires-Dist: django (>=4.0,<5.0)
Requires-Dist: flet
Requires-Dist: flet-core
Project-URL: Documentation, https://github.com/Marysia-Software-Limited/flet-django
Project-URL: Repository, https://github.com/Marysia-Software-Limited/flet-django
